pyinput/__init__.py
pyinput/pyinput.py
pyinput/pyinputkeycodes.py
pyinput-0.3.2.dist-info/LICENSE
pyinput-0.3.2.dist-info/METADATA
pyinput-0.3.2.dist-info/WHEEL
pyinput-0.3.2.dist-info/top_level.txt
pyinput-0.3.2.dist-info/RECORD
